blackscholes_python-0.10.7.dist-info/METADATA
blackscholes_python-0.10.7.dist-info/WHEEL
blackscholes_python-0.10.7.dist-info/license_files/LICENSE.md
blackscholes_python/__init__.py
blackscholes_python/__init__.pyi
blackscholes_python/py.typed
blackscholes_python/blackscholes_python.cpython-311-x86_64-linux-gnu.so
blackscholes_python-0.10.7.dist-info/RECORD
