Metadata-Version: 2.1
Name: blackscholes_python
Version: 0.10.7
Classifier: Programming Language :: Rust
Classifier: Programming Language :: Python :: Implementation :: CPython
Classifier: Programming Language :: Python :: Implementation :: PyPy
License-File: LICENSE.md
Summary: Black-Scholes option pricing model calculator
Keywords: finance,option,python,blackscholes,option-pricing
Author: Hayden Rose
License: MIT
Requires-Python: >=3.7
Project-URL: Source Code, https://github.com/hayden4r4/blackscholes-rust/tree/python_package
